lionshead/__init__.py
lionshead/linux.py
lionshead/util.py
lionshead-0.1.1.dist-info/DESCRIPTION.rst
lionshead-0.1.1.dist-info/METADATA
lionshead-0.1.1.dist-info/RECORD
lionshead-0.1.1.dist-info/WHEEL
lionshead-0.1.1.dist-info/entry_points.txt
lionshead-0.1.1.dist-info/metadata.json
lionshead-0.1.1.dist-info/top_level.txt
