Metadata-Version: 2.0
Name: lionshead
Version: 0.1.1
Summary: Detect OS/platforms
Home-page: https://github.com/natefoo/lionshead
Author: Nate Coraor
Author-email: nate@coraor.org
License: MIT
Keywords: platform os operating system
Platform: UNKNOWN
Classifier: License :: OSI Approved :: MIT License
Classifier: Natural Language :: English
Classifier: Operating System :: POSIX
Classifier: Programming Language :: Python
Classifier: Programming Language :: Python :: 2
Classifier: Programming Language :: Python :: 3
